README.rst
setup.py
datapot/__init__.py
datapot/iterators.py
datapot/utils.py
datapot.egg-info/PKG-INFO
datapot.egg-info/SOURCES.txt
datapot.egg-info/dependency_links.txt
datapot.egg-info/requires.txt
datapot.egg-info/top_level.txt
datapot/datasets/__init__.py
datapot/datasets/datasets.py
datapot/transformer/__init__.py
datapot/transformer/base_transformer.py
datapot/transformer/boolean_transformer.py
datapot/transformer/category_transformer.py
datapot/transformer/complex_transformer.py
datapot/transformer/group_dim_reduce_transformer.py
datapot/transformer/identity_transformer.py
datapot/transformer/numeric_transformer.py
datapot/transformer/ssa_transformer.py
datapot/transformer/text_transformer.py
datapot/transformer/timeseries_transformer.py
datapot/transformer/timestamp_transformer.py