Metadata-Version: 1.1
Name: datapot
Version: 0.1.2
Summary: Library for automatic feature extraction from JSON-datasets
Home-page: https://github.com/bashalex/datapot
Author: Nikita Savelyev
Author-email: n.a.savelyev@gmail.com
License: GNU v3.0
Platform: UNKNOWN
Classifier: Development Status :: 3 - Alpha
Classifier: License :: OSI Approved :: GNU General Public License v3 (GPLv3)
Classifier: Programming Language :: Python :: 3
Classifier: Programming Language :: Python :: 2
Classifier: Intended Audience :: Science/Research
Classifier: Intended Audience :: Developers
Classifier: Topic :: Scientific/Engineering
Classifier: Topic :: Software Development
